moc_prices_source/__init__.py
moc_prices_source/cli.py
moc_prices_source/cli_check.py
moc_prices_source/coins.py
moc_prices_source/computed_pairs.py
moc_prices_source/conf.py
moc_prices_source/database.py
moc_prices_source/from_db.py
moc_prices_source/my_logging.py
moc_prices_source/server.py
moc_prices_source/to_db.py
moc_prices_source/version.txt
moc_prices_source/weighing.py
moc_prices_source/data/database_default.json
moc_prices_source/data/redis_default.json
moc_prices_source/data/remote_weighing_default.json
moc_prices_source/data/weighing.json
moc_prices_source/engines/__init__.py
moc_prices_source/engines/bnb_usdt_binance.py
moc_prices_source/engines/bpro_btc_onchain.py
moc_prices_source/engines/btc_ars_argenbtc.py
moc_prices_source/engines/btc_ars_belo_app.py
moc_prices_source/engines/btc_ars_binance.py
moc_prices_source/engines/btc_ars_bitso.py
moc_prices_source/engines/btc_ars_buda.py
moc_prices_source/engines/btc_ars_buenbit.py
moc_prices_source/engines/btc_ars_coinbase.py
moc_prices_source/engines/btc_ars_cryptomkt.py
moc_prices_source/engines/btc_ars_decrypto.py
moc_prices_source/engines/btc_ars_lemoncash.py
moc_prices_source/engines/btc_ars_ripio.py
moc_prices_source/engines/btc_ars_ripio_exch.py
moc_prices_source/engines/btc_ars_rofex.py
moc_prices_source/engines/btc_ars_satoshitango.py
moc_prices_source/engines/btc_cop_bitso.py
moc_prices_source/engines/btc_cop_buda.py
moc_prices_source/engines/btc_cop_buenbit.py
moc_prices_source/engines/btc_cop_coinbase.py
moc_prices_source/engines/btc_cop_cryptomkt.py
moc_prices_source/engines/btc_usd_bitfinex.py
moc_prices_source/engines/btc_usd_bitgo.py
moc_prices_source/engines/btc_usd_bitstamp.py
moc_prices_source/engines/btc_usd_bittrex.py
moc_prices_source/engines/btc_usd_blockchain.py
moc_prices_source/engines/btc_usd_cex.py
moc_prices_source/engines/btc_usd_coinbase.py
moc_prices_source/engines/btc_usd_gemini.py
moc_prices_source/engines/btc_usd_itbit.py
moc_prices_source/engines/btc_usd_kraken.py
moneyonchain_prices_source-0.7.3.dist-info/METADATA
moneyonchain_prices_source-0.7.3.dist-info/WHEEL
moneyonchain_prices_source-0.7.3.dist-info/top_level.txt
moneyonchain_prices_source-0.7.3.dist-info/RECORD
