Metadata-Version: 2.2
Name: moneyonchain_prices_source
Version: 0.7.3
Summary: Prices source for MoC projects
Author: Juan S. Bokser
Author-email: juan.bokser@moneyonchain.com
Classifier: Intended Audience :: Developers
Classifier: Programming Language :: Python :: 3
Classifier: Programming Language :: Python :: 3.8
Requires-Python: >=3.8
Requires-Dist: click
Requires-Dist: tabulate
Requires-Dist: requests
Requires-Dist: influxdb
Requires-Dist: redis
Requires-Dist: bs4
Requires-Dist: lxml
Requires-Dist: web3
Requires-Dist: setuptools>=38.6.0
Requires-Dist: wheel>=0.31.0
Requires-Dist: twine>=1.11.0
Requires-Dist: flask-restx
Requires-Dist: flask_cors
Requires-Dist: cachelib
Requires-Dist: flask_caching
Dynamic: author
Dynamic: author-email
Dynamic: classifier
Dynamic: description
Dynamic: description-content-type
Dynamic: requires-dist
Dynamic: requires-python
Dynamic: summary
